Metadata-Version: 1.0
Name: x-mroy-0
Version: 0.0.0
Summary: a manager package
Home-page: https://github.com/Qingluan/xproj.git
Author: Qing luan
Author-email: darkhackdevil@gmail.com
License: MIT
Platform: UNKNOWN
